nctl/__init__.py
nctl/aws.py
nctl/logger.py
nctl/models.py
nctl/ngrok.py
nctl/squire.py
nctl-0.0.1.dist-info/LICENSE
nctl-0.0.1.dist-info/METADATA
nctl-0.0.1.dist-info/WHEEL
nctl-0.0.1.dist-info/entry_points.txt
nctl-0.0.1.dist-info/top_level.txt
nctl-0.0.1.dist-info/RECORD
