Metadata-Version: 2.1
Name: nctl
Version: 0.0.1
Summary: Fuses ngrok and CloudFront offering a fully automated solution.
Author-email: Vignesh Rao <svignesh1793@gmail.com>
License: MIT License
Project-URL: Homepage, https://github.com/thevickypedia/nctl
Project-URL: Docs, https://thevickypedia.github.io/nctl
Project-URL: Source, https://github.com/thevickypedia/nctl
Project-URL: Bug Tracker, https://github.com/thevickypedia/nctl/issues
Project-URL: Release Notes, https://github.com/thevickypedia/nctl/blob/main/release_notes.rst
Keywords: nctl,ngrok,cloudfront
Classifier: License :: OSI Approved :: MIT License
Classifier: Programming Language :: Python :: 3.10
Classifier: Programming Language :: Python :: 3.11
Classifier: Development Status :: 5 - Production/Stable
Classifier: Operating System :: MacOS :: MacOS X
Classifier: Operating System :: Microsoft :: Windows
Classifier: Operating System :: POSIX :: Linux
Requires-Python: >=3.10
License-File: LICENSE
Requires-Dist: boto3==1.34.158
Requires-Dist: botocore==1.34.158
Requires-Dist: click==8.1.7
Requires-Dist: pydantic==2.8.2
Requires-Dist: pydantic-settings==2.4.0
Requires-Dist: PyYaml==6.0.2
Provides-Extra: dev
Requires-Dist: sphinx==5.1.1; extra == "dev"
Requires-Dist: pre-commit; extra == "dev"
Requires-Dist: recommonmark; extra == "dev"
Requires-Dist: gitverse; extra == "dev"
